package com.kfb.a;

import java.util.ArrayList;
import java.util.List;

public final class c
{
  static String A = "";
  static String B = "";
  static String C = "";
  public static List D = new ArrayList();
  static String a = "";
  static String b = "";
  static String c = "";
  static String d = "";
  static String e = "";
  static String f = "";
  static String g = "";
  static String h = "";
  static String i = "";
  static String j = "";
  static String k = "";
  static String l = "";
  static String m = "";
  static String n = "";
  static String o = "";
  static String p = "";
  static String q = "";
  static String r = "";
  static String s = "";
  static String t = "";
  static String u = "";
  static String v = "";
  static String w = "";
  static String x = "";
  static String y = "";
  static String z = "";

  // ERROR //
  public static void a(android.content.Context paramContext)
  {
    // Byte code:
    //   0: aconst_null
    //   1: astore_1
    //   2: getstatic 105	com/kfb/a/c:D	Ljava/util/List;
    //   5: invokeinterface 116 1 0
    //   10: new 118	java/lang/String
    //   13: dup
    //   14: ldc 120
    //   16: invokestatic 125	com/kfb/a/b:a	(Ljava/lang/String;)[B
    //   19: invokespecial 128	java/lang/String:<init>	([B)V
    //   22: astore_2
    //   23: aload_0
    //   24: invokevirtual 134	android/content/Context:getAssets	()Landroid/content/res/AssetManager;
    //   27: aload_2
    //   28: invokevirtual 140	android/content/res/AssetManager:open	(Ljava/lang/String;)Ljava/io/InputStream;
    //   31: astore 11
    //   33: aload 11
    //   35: astore 6
    //   37: new 142	java/io/DataInputStream
    //   40: dup
    //   41: aload 6
    //   43: invokespecial 145	java/io/DataInputStream:<init>	(Ljava/io/InputStream;)V
    //   46: astore 12
    //   48: aload 12
    //   50: aload 12
    //   52: invokevirtual 149	java/io/DataInputStream:readInt	()I
    //   55: newarray byte
    //   57: invokevirtual 153	java/io/DataInputStream:read	([B)I
    //   60: pop
    //   61: aload 12
    //   63: aload 12
    //   65: invokevirtual 149	java/io/DataInputStream:readInt	()I
    //   68: newarray byte
    //   70: invokevirtual 153	java/io/DataInputStream:read	([B)I
    //   73: pop
    //   74: aload 12
    //   76: aload 12
    //   78: invokevirtual 149	java/io/DataInputStream:readInt	()I
    //   81: newarray byte
    //   83: invokevirtual 153	java/io/DataInputStream:read	([B)I
    //   86: pop
    //   87: aload 12
    //   89: invokevirtual 149	java/io/DataInputStream:readInt	()I
    //   92: pop
    //   93: new 142	java/io/DataInputStream
    //   96: dup
    //   97: aload 6
    //   99: invokespecial 145	java/io/DataInputStream:<init>	(Ljava/io/InputStream;)V
    //   102: astore_1
    //   103: new 155	java/io/BufferedReader
    //   106: dup
    //   107: new 157	java/io/InputStreamReader
    //   110: dup
    //   111: aload_1
    //   112: invokespecial 158	java/io/InputStreamReader:<init>	(Ljava/io/InputStream;)V
    //   115: invokespecial 161	java/io/BufferedReader:<init>	(Ljava/io/Reader;)V
    //   118: astore 17
    //   120: aload 17
    //   122: invokevirtual 165	java/io/BufferedReader:readLine	()Ljava/lang/String;
    //   125: astore 18
    //   127: aload 18
    //   129: ifnull +28 -> 157
    //   132: getstatic 105	com/kfb/a/c:D	Ljava/util/List;
    //   135: aload 18
    //   137: invokeinterface 169 2 0
    //   142: pop
    //   143: aload 17
    //   145: invokevirtual 165	java/io/BufferedReader:readLine	()Ljava/lang/String;
    //   148: astore 20
    //   150: aload 20
    //   152: astore 18
    //   154: goto -27 -> 127
    //   157: new 118	java/lang/String
    //   160: dup
    //   161: getstatic 105	com/kfb/a/c:D	Ljava/util/List;
    //   164: iconst_0
    //   165: invokeinterface 173 2 0
    //   170: checkcast 118	java/lang/String
    //   173: invokestatic 125	com/kfb/a/b:a	(Ljava/lang/String;)[B
    //   176: invokespecial 128	java/lang/String:<init>	([B)V
    //   179: putstatic 42	com/kfb/a/c:a	Ljava/lang/String;
    //   182: new 118	java/lang/String
    //   185: dup
    //   186: getstatic 105	com/kfb/a/c:D	Ljava/util/List;
    //   189: iconst_1
    //   190: invokeinterface 173 2 0
    //   195: checkcast 118	java/lang/String
    //   198: invokestatic 125	com/kfb/a/b:a	(Ljava/lang/String;)[B
    //   201: invokespecial 128	java/lang/String:<init>	([B)V
    //   204: putstatic 44	com/kfb/a/c:b	Ljava/lang/String;
    //   207: new 118	java/lang/String
    //   210: dup
    //   211: getstatic 105	com/kfb/a/c:D	Ljava/util/List;
    //   214: iconst_2
    //   215: invokeinterface 173 2 0
    //   220: checkcast 118	java/lang/String
    //   223: invokestatic 125	com/kfb/a/b:a	(Ljava/lang/String;)[B
    //   226: invokespecial 128	java/lang/String:<init>	([B)V
    //   229: putstatic 46	com/kfb/a/c:c	Ljava/lang/String;
    //   232: new 118	java/lang/String
    //   235: dup
    //   236: getstatic 105	com/kfb/a/c:D	Ljava/util/List;
    //   239: iconst_3
    //   240: invokeinterface 173 2 0
    //   245: checkcast 118	java/lang/String
    //   248: invokestatic 125	com/kfb/a/b:a	(Ljava/lang/String;)[B
    //   251: invokespecial 128	java/lang/String:<init>	([B)V
    //   254: putstatic 74	com/kfb/a/c:q	Ljava/lang/String;
    //   257: new 118	java/lang/String
    //   260: dup
    //   261: getstatic 105	com/kfb/a/c:D	Ljava/util/List;
    //   264: iconst_4
    //   265: invokeinterface 173 2 0
    //   270: checkcast 118	java/lang/String
    //   273: invokestatic 125	com/kfb/a/b:a	(Ljava/lang/String;)[B
    //   276: invokespecial 128	java/lang/String:<init>	([B)V
    //   279: putstatic 48	com/kfb/a/c:d	Ljava/lang/String;
    //   282: new 118	java/lang/String
    //   285: dup
    //   286: getstatic 105	com/kfb/a/c:D	Ljava/util/List;
    //   289: iconst_5
    //   290: invokeinterface 173 2 0
    //   295: checkcast 118	java/lang/String
    //   298: invokestatic 125	com/kfb/a/b:a	(Ljava/lang/String;)[B
    //   301: invokespecial 128	java/lang/String:<init>	([B)V
    //   304: putstatic 50	com/kfb/a/c:e	Ljava/lang/String;
    //   307: new 118	java/lang/String
    //   310: dup
    //   311: getstatic 105	com/kfb/a/c:D	Ljava/util/List;
    //   314: bipush 6
    //   316: invokeinterface 173 2 0
    //   321: checkcast 118	java/lang/String
    //   324: invokestatic 125	com/kfb/a/b:a	(Ljava/lang/String;)[B
    //   327: invokespecial 128	java/lang/String:<init>	([B)V
    //   330: putstatic 52	com/kfb/a/c:f	Ljava/lang/String;
    //   333: new 118	java/lang/String
    //   336: dup
    //   337: getstatic 105	com/kfb/a/c:D	Ljava/util/List;
    //   340: bipush 7
    //   342: invokeinterface 173 2 0
    //   347: checkcast 118	java/lang/String
    //   350: invokestatic 125	com/kfb/a/b:a	(Ljava/lang/String;)[B
    //   353: invokespecial 128	java/lang/String:<init>	([B)V
    //   356: putstatic 54	com/kfb/a/c:g	Ljava/lang/String;
    //   359: new 118	java/lang/String
    //   362: dup
    //   363: getstatic 105	com/kfb/a/c:D	Ljava/util/List;
    //   366: bipush 8
    //   368: invokeinterface 173 2 0
    //   373: checkcast 118	java/lang/String
    //   376: invokestatic 125	com/kfb/a/b:a	(Ljava/lang/String;)[B
    //   379: invokespecial 128	java/lang/String:<init>	([B)V
    //   382: putstatic 56	com/kfb/a/c:h	Ljava/lang/String;
    //   385: new 118	java/lang/String
    //   388: dup
    //   389: getstatic 105	com/kfb/a/c:D	Ljava/util/List;
    //   392: bipush 9
    //   394: invokeinterface 173 2 0
    //   399: checkcast 118	java/lang/String
    //   402: invokestatic 125	com/kfb/a/b:a	(Ljava/lang/String;)[B
    //   405: invokespecial 128	java/lang/String:<init>	([B)V
    //   408: putstatic 58	com/kfb/a/c:i	Ljava/lang/String;
    //   411: new 118	java/lang/String
    //   414: dup
    //   415: getstatic 105	com/kfb/a/c:D	Ljava/util/List;
    //   418: bipush 10
    //   420: invokeinterface 173 2 0
    //   425: checkcast 118	java/lang/String
    //   428: invokestatic 125	com/kfb/a/b:a	(Ljava/lang/String;)[B
    //   431: invokespecial 128	java/lang/String:<init>	([B)V
    //   434: putstatic 60	com/kfb/a/c:j	Ljava/lang/String;
    //   437: new 118	java/lang/String
    //   440: dup
    //   441: getstatic 105	com/kfb/a/c:D	Ljava/util/List;
    //   444: bipush 11
    //   446: invokeinterface 173 2 0
    //   451: checkcast 118	java/lang/String
    //   454: invokestatic 125	com/kfb/a/b:a	(Ljava/lang/String;)[B
    //   457: invokespecial 128	java/lang/String:<init>	([B)V
    //   460: putstatic 62	com/kfb/a/c:k	Ljava/lang/String;
    //   463: new 118	java/lang/String
    //   466: dup
    //   467: getstatic 105	com/kfb/a/c:D	Ljava/util/List;
    //   470: bipush 12
    //   472: invokeinterface 173 2 0
    //   477: checkcast 118	java/lang/String
    //   480: invokestatic 125	com/kfb/a/b:a	(Ljava/lang/String;)[B
    //   483: invokespecial 128	java/lang/String:<init>	([B)V
    //   486: putstatic 64	com/kfb/a/c:l	Ljava/lang/String;
    //   489: new 118	java/lang/String
    //   492: dup
    //   493: getstatic 105	com/kfb/a/c:D	Ljava/util/List;
    //   496: bipush 13
    //   498: invokeinterface 173 2 0
    //   503: checkcast 118	java/lang/String
    //   506: invokestatic 125	com/kfb/a/b:a	(Ljava/lang/String;)[B
    //   509: invokespecial 128	java/lang/String:<init>	([B)V
    //   512: putstatic 66	com/kfb/a/c:m	Ljava/lang/String;
    //   515: new 118	java/lang/String
    //   518: dup
    //   519: getstatic 105	com/kfb/a/c:D	Ljava/util/List;
    //   522: bipush 14
    //   524: invokeinterface 173 2 0
    //   529: checkcast 118	java/lang/String
    //   532: invokestatic 125	com/kfb/a/b:a	(Ljava/lang/String;)[B
    //   535: invokespecial 128	java/lang/String:<init>	([B)V
    //   538: putstatic 68	com/kfb/a/c:n	Ljava/lang/String;
    //   541: new 118	java/lang/String
    //   544: dup
    //   545: getstatic 105	com/kfb/a/c:D	Ljava/util/List;
    //   548: bipush 15
    //   550: invokeinterface 173 2 0
    //   555: checkcast 118	java/lang/String
    //   558: invokestatic 125	com/kfb/a/b:a	(Ljava/lang/String;)[B
    //   561: invokespecial 128	java/lang/String:<init>	([B)V
    //   564: putstatic 70	com/kfb/a/c:o	Ljava/lang/String;
    //   567: new 118	java/lang/String
    //   570: dup
    //   571: getstatic 105	com/kfb/a/c:D	Ljava/util/List;
    //   574: bipush 16
    //   576: invokeinterface 173 2 0
    //   581: checkcast 118	java/lang/String
    //   584: invokestatic 125	com/kfb/a/b:a	(Ljava/lang/String;)[B
    //   587: invokespecial 128	java/lang/String:<init>	([B)V
    //   590: putstatic 72	com/kfb/a/c:p	Ljava/lang/String;
    //   593: new 118	java/lang/String
    //   596: dup
    //   597: getstatic 105	com/kfb/a/c:D	Ljava/util/List;
    //   600: bipush 17
    //   602: invokeinterface 173 2 0
    //   607: checkcast 118	java/lang/String
    //   610: invokestatic 125	com/kfb/a/b:a	(Ljava/lang/String;)[B
    //   613: invokespecial 128	java/lang/String:<init>	([B)V
    //   616: putstatic 76	com/kfb/a/c:r	Ljava/lang/String;
    //   619: new 118	java/lang/String
    //   622: dup
    //   623: getstatic 105	com/kfb/a/c:D	Ljava/util/List;
    //   626: bipush 18
    //   628: invokeinterface 173 2 0
    //   633: checkcast 118	java/lang/String
    //   636: invokestatic 125	com/kfb/a/b:a	(Ljava/lang/String;)[B
    //   639: invokespecial 128	java/lang/String:<init>	([B)V
    //   642: putstatic 78	com/kfb/a/c:s	Ljava/lang/String;
    //   645: new 118	java/lang/String
    //   648: dup
    //   649: getstatic 105	com/kfb/a/c:D	Ljava/util/List;
    //   652: bipush 19
    //   654: invokeinterface 173 2 0
    //   659: checkcast 118	java/lang/String
    //   662: invokestatic 125	com/kfb/a/b:a	(Ljava/lang/String;)[B
    //   665: invokespecial 128	java/lang/String:<init>	([B)V
    //   668: putstatic 80	com/kfb/a/c:t	Ljava/lang/String;
    //   671: new 118	java/lang/String
    //   674: dup
    //   675: getstatic 105	com/kfb/a/c:D	Ljava/util/List;
    //   678: bipush 20
    //   680: invokeinterface 173 2 0
    //   685: checkcast 118	java/lang/String
    //   688: invokestatic 125	com/kfb/a/b:a	(Ljava/lang/String;)[B
    //   691: invokespecial 128	java/lang/String:<init>	([B)V
    //   694: putstatic 82	com/kfb/a/c:u	Ljava/lang/String;
    //   697: new 118	java/lang/String
    //   700: dup
    //   701: getstatic 105	com/kfb/a/c:D	Ljava/util/List;
    //   704: bipush 21
    //   706: invokeinterface 173 2 0
    //   711: checkcast 118	java/lang/String
    //   714: invokestatic 125	com/kfb/a/b:a	(Ljava/lang/String;)[B
    //   717: invokespecial 128	java/lang/String:<init>	([B)V
    //   720: putstatic 84	com/kfb/a/c:v	Ljava/lang/String;
    //   723: new 118	java/lang/String
    //   726: dup
    //   727: getstatic 105	com/kfb/a/c:D	Ljava/util/List;
    //   730: bipush 22
    //   732: invokeinterface 173 2 0
    //   737: checkcast 118	java/lang/String
    //   740: invokestatic 125	com/kfb/a/b:a	(Ljava/lang/String;)[B
    //   743: invokespecial 128	java/lang/String:<init>	([B)V
    //   746: putstatic 86	com/kfb/a/c:w	Ljava/lang/String;
    //   749: new 118	java/lang/String
    //   752: dup
    //   753: getstatic 105	com/kfb/a/c:D	Ljava/util/List;
    //   756: bipush 23
    //   758: invokeinterface 173 2 0
    //   763: checkcast 118	java/lang/String
    //   766: invokestatic 125	com/kfb/a/b:a	(Ljava/lang/String;)[B
    //   769: invokespecial 128	java/lang/String:<init>	([B)V
    //   772: putstatic 88	com/kfb/a/c:x	Ljava/lang/String;
    //   775: new 118	java/lang/String
    //   778: dup
    //   779: getstatic 105	com/kfb/a/c:D	Ljava/util/List;
    //   782: bipush 24
    //   784: invokeinterface 173 2 0
    //   789: checkcast 118	java/lang/String
    //   792: invokestatic 125	com/kfb/a/b:a	(Ljava/lang/String;)[B
    //   795: invokespecial 128	java/lang/String:<init>	([B)V
    //   798: putstatic 90	com/kfb/a/c:y	Ljava/lang/String;
    //   801: new 118	java/lang/String
    //   804: dup
    //   805: getstatic 105	com/kfb/a/c:D	Ljava/util/List;
    //   808: bipush 25
    //   810: invokeinterface 173 2 0
    //   815: checkcast 118	java/lang/String
    //   818: invokestatic 125	com/kfb/a/b:a	(Ljava/lang/String;)[B
    //   821: invokespecial 128	java/lang/String:<init>	([B)V
    //   824: putstatic 92	com/kfb/a/c:z	Ljava/lang/String;
    //   827: new 118	java/lang/String
    //   830: dup
    //   831: getstatic 105	com/kfb/a/c:D	Ljava/util/List;
    //   834: bipush 26
    //   836: invokeinterface 173 2 0
    //   841: checkcast 118	java/lang/String
    //   844: invokestatic 125	com/kfb/a/b:a	(Ljava/lang/String;)[B
    //   847: invokespecial 128	java/lang/String:<init>	([B)V
    //   850: putstatic 94	com/kfb/a/c:A	Ljava/lang/String;
    //   853: new 118	java/lang/String
    //   856: dup
    //   857: getstatic 105	com/kfb/a/c:D	Ljava/util/List;
    //   860: bipush 27
    //   862: invokeinterface 173 2 0
    //   867: checkcast 118	java/lang/String
    //   870: invokestatic 125	com/kfb/a/b:a	(Ljava/lang/String;)[B
    //   873: invokespecial 128	java/lang/String:<init>	([B)V
    //   876: putstatic 96	com/kfb/a/c:B	Ljava/lang/String;
    //   879: new 118	java/lang/String
    //   882: dup
    //   883: getstatic 105	com/kfb/a/c:D	Ljava/util/List;
    //   886: bipush 28
    //   888: invokeinterface 173 2 0
    //   893: checkcast 118	java/lang/String
    //   896: invokestatic 125	com/kfb/a/b:a	(Ljava/lang/String;)[B
    //   899: invokespecial 128	java/lang/String:<init>	([B)V
    //   902: putstatic 98	com/kfb/a/c:C	Ljava/lang/String;
    //   905: aload_1
    //   906: invokevirtual 176	java/io/DataInputStream:close	()V
    //   909: aload 6
    //   911: ifnull +8 -> 919
    //   914: aload 6
    //   916: invokevirtual 179	java/io/InputStream:close	()V
    //   919: return
    //   920: astore 21
    //   922: aload 21
    //   924: invokevirtual 182	java/lang/Exception:printStackTrace	()V
    //   927: goto -22 -> 905
    //   930: astore_3
    //   931: aload 6
    //   933: astore 4
    //   935: aload_3
    //   936: invokevirtual 182	java/lang/Exception:printStackTrace	()V
    //   939: aload_1
    //   940: ifnull +7 -> 947
    //   943: aload_1
    //   944: invokevirtual 176	java/io/DataInputStream:close	()V
    //   947: aload 4
    //   949: ifnull -30 -> 919
    //   952: aload 4
    //   954: invokevirtual 179	java/io/InputStream:close	()V
    //   957: return
    //   958: astore 9
    //   960: aload 9
    //   962: invokevirtual 183	java/io/IOException:printStackTrace	()V
    //   965: return
    //   966: astore 22
    //   968: aload 22
    //   970: invokevirtual 183	java/io/IOException:printStackTrace	()V
    //   973: goto -64 -> 909
    //   976: astore 23
    //   978: aload 23
    //   980: invokevirtual 183	java/io/IOException:printStackTrace	()V
    //   983: return
    //   984: astore 10
    //   986: aload 10
    //   988: invokevirtual 183	java/io/IOException:printStackTrace	()V
    //   991: goto -44 -> 947
    //   994: astore 5
    //   996: aconst_null
    //   997: astore 6
    //   999: aload_1
    //   1000: ifnull +7 -> 1007
    //   1003: aload_1
    //   1004: invokevirtual 176	java/io/DataInputStream:close	()V
    //   1007: aload 6
    //   1009: ifnull +8 -> 1017
    //   1012: aload 6
    //   1014: invokevirtual 179	java/io/InputStream:close	()V
    //   1017: aload 5
    //   1019: athrow
    //   1020: astore 8
    //   1022: aload 8
    //   1024: invokevirtual 183	java/io/IOException:printStackTrace	()V
    //   1027: goto -20 -> 1007
    //   1030: astore 7
    //   1032: aload 7
    //   1034: invokevirtual 183	java/io/IOException:printStackTrace	()V
    //   1037: goto -20 -> 1017
    //   1040: astore 5
    //   1042: goto -43 -> 999
    //   1045: astore 5
    //   1047: aload 12
    //   1049: astore_1
    //   1050: goto -51 -> 999
    //   1053: astore 5
    //   1055: aload 4
    //   1057: astore 6
    //   1059: goto -60 -> 999
    //   1062: astore_3
    //   1063: aconst_null
    //   1064: astore_1
    //   1065: aconst_null
    //   1066: astore 4
    //   1068: goto -133 -> 935
    //   1071: astore_3
    //   1072: aload 12
    //   1074: astore_1
    //   1075: aload 6
    //   1077: astore 4
    //   1079: goto -144 -> 935
    //
    // Exception table:
    //   from	to	target	type
    //   157	905	920	java/lang/Exception
    //   37	48	930	java/lang/Exception
    //   103	127	930	java/lang/Exception
    //   132	150	930	java/lang/Exception
    //   922	927	930	java/lang/Exception
    //   952	957	958	java/io/IOException
    //   905	909	966	java/io/IOException
    //   914	919	976	java/io/IOException
    //   943	947	984	java/io/IOException
    //   10	33	994	finally
    //   1003	1007	1020	java/io/IOException
    //   1012	1017	1030	java/io/IOException
    //   37	48	1040	finally
    //   103	127	1040	finally
    //   132	150	1040	finally
    //   157	905	1040	finally
    //   922	927	1040	finally
    //   48	103	1045	finally
    //   935	939	1053	finally
    //   10	33	1062	java/lang/Exception
    //   48	103	1071	java/lang/Exception
  }
}

/* Location:           D:\yinxm\Android\work\拍卖\apktool\artrade\classes_dex2jar.jar
 * Qualified Name:     com.kfb.a.c
 * JD-Core Version:    0.6.2
 */